lazy_action/__init__.py
lazy_action/lazy_action.py
lazy_action-1.0.2.dist-info/METADATA
lazy_action-1.0.2.dist-info/WHEEL
lazy_action-1.0.2.dist-info/top_level.txt
lazy_action-1.0.2.dist-info/RECORD
