Metadata-Version: 2.4
Name: lazy_action
Version: 1.0.2
Summary: lazy_action make your func lazy
Home-page: https://github.com/iridesc/lazy_action
Author: Irid
Author-email: irid.zzy@gmail.com
Classifier: Programming Language :: Python :: 3
Classifier: License :: OSI Approved :: MIT License
Classifier: Operating System :: OS Independent
Requires-Dist: diskcache
Requires-Dist: cachelib
Requires-Dist: portalocker
Dynamic: author
Dynamic: author-email
Dynamic: classifier
Dynamic: description
Dynamic: description-content-type
Dynamic: home-page
Dynamic: requires-dist
Dynamic: summary
